NTHU_NLPLab_toolkit/__init__.py
NTHU_NLPLab_toolkit/requirements.txt
NTHU_NLPLab_toolkit/Linggle/__init__.py
NTHU_NLPLab_toolkit/Linggle/api.py
NTHU_NLPLab_toolkit/Linggle/config.py
NTHU_NLPLab_toolkit-0.0.1.dist-info/METADATA
NTHU_NLPLab_toolkit-0.0.1.dist-info/WHEEL
NTHU_NLPLab_toolkit-0.0.1.dist-info/top_level.txt
NTHU_NLPLab_toolkit-0.0.1.dist-info/RECORD
