Metadata-Version: 2.1
Name: NTHU-NLPLab-toolkit
Version: 0.0.1
Summary: This toolkit is maintained by NTHU NLP Lab
Home-page: https://github.com/NTHU-NLPLAB/NLPLab_toolkit
Author: sappy5678
Author-email: sappy@nlplab.cc
License: UNKNOWN
Platform: UNKNOWN
Classifier: Programming Language :: Python :: 3
Classifier: Operating System :: OS Independent
Requires-Python: >=3.6
Requires-Dist: requests (>=2.22.0)
